rexpi/__init__.py
rexpi/cheb.py
rexpi/errorestimates.py
rexpi/expimv.py
rexpi/pade.py
rexpi/unitarybestapprox.py
rexpi-0.0.4.dist-info/METADATA
rexpi-0.0.4.dist-info/WHEEL
rexpi-0.0.4.dist-info/licenses/LICENSE
rexpi-0.0.4.dist-info/RECORD
